anna_client/__init__.py
anna_client/client.py
anna_client/graphql.py
anna_client-1.1.9.dist-info/METADATA
anna_client-1.1.9.dist-info/WHEEL
anna_client-1.1.9.dist-info/top_level.txt
anna_client-1.1.9.dist-info/RECORD
