Metadata-Version: 2.1
Name: anna-client
Version: 1.1.9
Summary: anna API client
Home-page: https://github.com/patrikpihlstrom/anna-client
Author: Patrik Pihlstrom
Author-email: patrik.pihlstrom@gmail.com
License: UNKNOWN
Platform: UNKNOWN
Requires-Dist: requests
Requires-Dist: graphqlclient
